_pvframework_version.py
pvframework/__init__.py
pvframework/analysis.py
pvframework/errors.py
pvframework/execution.py
pvframework/py.typed
pvframework/types.py
pvframework/validator.py
pvframework/mapped_validators/__init__.py
pvframework/mapped_validators/path_map.py
pvframework/mapped_validators/query_map.py
pvframework/mapped_validators/query_parallel_map.py
pvframework/utils/__init__.py
pvframework/utils/frame_functions.py
pvframework/utils/query_object.py
pvframework-0.1.2.dist-info/METADATA
pvframework-0.1.2.dist-info/WHEEL
pvframework-0.1.2.dist-info/licenses/LICENSE
pvframework-0.1.2.dist-info/RECORD
